pyckelhaube/__init__.py
pyckelhaube/exceptions.py
pyckelhaube/helm_chart.py
pyckelhaube/render.py
pyckelhaube/resource.py
pyckelhaube/template.py
pyckelhaube-0.2.0.dist-info/METADATA
pyckelhaube-0.2.0.dist-info/WHEEL
pyckelhaube-0.2.0.dist-info/licenses/LICENSE.md
pyckelhaube-0.2.0.dist-info/RECORD
