Metadata-Version: 2.4
Name: pyckelhaube
Version: 0.2.0
Summary: A Python library for testing Helm chart rendering
License: MIT
License-File: LICENSE.md
Author: Quantraum
Author-email: support@quantraum.com
Requires-Python: >=3.12,<4.0
Classifier: License :: OSI Approved :: MIT License
Classifier: Programming Language :: Python :: 3
Classifier: Programming Language :: Python :: 3.12
Classifier: Programming Language :: Python :: 3.13
Classifier: Programming Language :: Python :: 3.14
Requires-Dist: pyyaml (>=6.0,<7.0)
